README.md
cryptux
setup.cfg
setup.py
CryptoWallets.egg-info/PKG-INFO
CryptoWallets.egg-info/SOURCES.txt
CryptoWallets.egg-info/dependency_links.txt
CryptoWallets.egg-info/top_level.txt
bitcoin/__init__.py
bitcoin/base58.py
bitcoin/constants.py
bitcoin/gen_addr.py
bitcoin/hashes.py
bitcoin/test_bitcoin_gen_addr.py
bitcoin/wif.py