Metadata-Version: 1.0
Name: CryptoWallets
Version: 0.0.1
Summary: Sample wallets for Cryptocurrencies
Home-page: https://github.com/VISCHub/crypto-wallets
Author: Viet Le
Author-email: vietlq85@gmail.com
License: UNKNOWN
Keywords: crypto,hdw,wallet,bitcoin,ether
Platform: UNKNOWN
